xattr_compat/__init__.py
xattr_compat/darwin.py
xattr_compat/freebsd.py
xattr_compat-1.0.0.dist-info/LICENSE
xattr_compat-1.0.0.dist-info/METADATA
xattr_compat-1.0.0.dist-info/WHEEL
xattr_compat-1.0.0.dist-info/top_level.txt
xattr_compat-1.0.0.dist-info/RECORD
