Metadata-Version: 2.1
Name: xattr-compat
Version: 1.0.0
Summary: Multi-platform extended attributes support
Home-page: https://github.com/dgilman/xattr_compat
Author: David Gilman
Author-email: davidgilman1@gmail.com
License: UNKNOWN
Project-URL: Bug Reports, https://github.com/dgilman/xattr_compat/issues
Project-URL: Source, https://github.com/dgilman/xattr_compat/
Platform: UNKNOWN
Classifier: Development Status :: 5 - Production/Stable
Classifier: Intended Audience :: Developers
Classifier: Topic :: Software Development :: Libraries
Classifier: License :: OSI Approved :: MIT License
Classifier: Programming Language :: Python :: 3
Classifier: Programming Language :: Python :: 3.6
Classifier: Programming Language :: Python :: 3.7
Classifier: Programming Language :: Python :: 3.8
Classifier: Programming Language :: Python :: 3.9
Classifier: Programming Language :: Python :: 3 :: Only
Classifier: Operating System :: POSIX :: Linux
Classifier: Environment :: MacOS X
Classifier: Operating System :: POSIX :: BSD :: FreeBSD
Classifier: Operating System :: POSIX :: BSD :: NetBSD
Requires-Python: >=3.6
